README.md
setup.py
youtube_channel_videos_scraper_bot/__init__.py
youtube_channel_videos_scraper_bot.egg-info/PKG-INFO
youtube_channel_videos_scraper_bot.egg-info/SOURCES.txt
youtube_channel_videos_scraper_bot.egg-info/dependency_links.txt
youtube_channel_videos_scraper_bot.egg-info/requires.txt
youtube_channel_videos_scraper_bot.egg-info/top_level.txt