Metadata-Version: 2.1
Name: youtube-channel-videos-scraper-bot
Version: 1.0.0
Summary: A python library to scrape channel videos data from youtube automatically.
Home-page: https://youtube-api.datakund.com/en/latest/
Author: DataKund
Author-email: datakund@gmail.com
License: Apache License 2.0
Keywords: youtube python bot_studio channel videos scraper data web-scraping
Platform: UNKNOWN
